{
  "meta": {
    "title": "Planos e Preços | JustoAI - Gestão Jurídica Inteligente",
    "description": "Escolha o plano ideal para seu escritório. Teste grátis por 7 dias, sem cartão de crédito.",
    "annual_discount_pct": 0.15
  },
  "copy": {
    "hero": {
      "headline": "Planos transparentes",
      "subheadline": "Escolha o plano ideal para o seu escritório. Sem taxas ocultas, sem surpresas."
    },
    "disclaimers": {
      "reports": "* Relatórios estão sujeitos a limites de fair-use conforme o plano contratado.",
      "taxes": "** Valores não incluem impostos conforme legislação vigente.",
      "fifo": "*** Créditos expiram seguindo a regra FIFO (primeiro a entrar, primeiro a sair)."
    }
  },
  "plans": [
    {
      "id": "starter",
      "name": "Starter",
      "subtitle": "Para pequenos escritórios começando com automação",
      "price_monthly": 297,
      "price_annual": 250.45,
      "trial_days": 7,
      "popular": false,
      "custom_pricing": false,
      "highlighted_features": [
        "Até 50 processos monitorados",
        "20 relatórios/mês",
        "36 créditos de relatório/mês",
        "12 análises completas/mês",
        "Suporte por email"
      ],
      "features": {
        "processes": 50,
        "reports_monthly": 20,
        "report_credits": 36,
        "full_credits": 12,
        "users": 3,
        "support": "email"
      }
    },
    {
      "id": "professional",
      "name": "Professional",
      "subtitle": "Para escritórios em crescimento que precisam de mais poder",
      "price_monthly": 697,
      "price_annual": 592.45,
      "trial_days": 7,
      "popular": true,
      "custom_pricing": false,
      "highlighted_features": [
        "Até 200 processos monitorados",
        "60 relatórios/mês",
        "120 créditos de relatório/mês",
        "40 análises completas/mês",
        "Usuários ilimitados",
        "Suporte prioritário",
        "Relatórios personalizados",
        "API access"
      ],
      "features": {
        "processes": 200,
        "reports_monthly": 60,
        "report_credits": 120,
        "full_credits": 40,
        "users": -1,
        "support": "priority",
        "custom_reports": true,
        "api_access": true
      }
    },
    {
      "id": "enterprise",
      "name": "Enterprise",
      "subtitle": "Para grandes escritórios com necessidades personalizadas",
      "price_monthly": null,
      "price_annual": null,
      "trial_days": 14,
      "popular": false,
      "custom_pricing": true,
      "highlighted_features": [
        "Processos ilimitados",
        "Relatórios ilimitados",
        "Créditos personalizados",
        "Análises ilimitadas",
        "Usuários ilimitados",
        "Suporte dedicado 24/7",
        "Treinamento personalizado",
        "Integrações customizadas",
        "SLA garantido"
      ],
      "features": {
        "processes": -1,
        "reports_monthly": -1,
        "report_credits": -1,
        "full_credits": -1,
        "users": -1,
        "support": "dedicated",
        "custom_reports": true,
        "api_access": true,
        "sla": true,
        "training": true
      }
    }
  ],
  "features_matrix": {
    "categories": [
      {
        "name": "Monitoramento",
      "features": [
        {
          "name": "Processos monitorados",
          "starter": "50",
          "professional": "200",
          "enterprise": "Ilimitado"
        },
        {
          "name": "Sincronização automática",
          "starter": true,
          "professional": true,
          "enterprise": true
        },
        {
          "name": "Alertas em tempo real",
          "starter": true,
          "professional": true,
          "enterprise": true
        },
        {
          "name": "Integração com tribunais",
          "starter": "Básica",
          "professional": "Completa",
          "enterprise": "Personalizada"
        }
      ]
    },
      {
        "name": "Relatórios",
      "features": [
        {
          "name": "Relatórios mensais",
          "starter": "20",
          "professional": "60",
          "enterprise": "Ilimitado"
        },
        {
          "name": "Créditos de relatório/mês",
          "starter": "36",
          "professional": "120",
          "enterprise": "Personalizado"
        },
        {
          "name": "Análises completas/mês",
          "starter": "12",
          "professional": "40",
          "enterprise": "Ilimitado"
        },
        {
          "name": "Personalização de marca",
          "starter": false,
          "professional": true,
          "enterprise": true
        }
      ]
    },
      {
        "name": "Inteligência Artificial",
      "features": [
        {
          "name": "Análise de documentos",
          "starter": true,
          "professional": true,
          "enterprise": true
        },
        {
          "name": "Resumos automáticos",
          "starter": true,
          "professional": true,
          "enterprise": true
        },
        {
          "name": "Extração de dados",
          "starter": "Básica",
          "professional": "Avançada",
          "enterprise": "Personalizada"
        },
        {
          "name": "Modelos de IA dedicados",
          "starter": false,
          "professional": false,
          "enterprise": true
        }
      ]
    },
      {
        "name": "Colaboração",
      "features": [
        {
          "name": "Usuários incluídos",
          "starter": "3",
          "professional": "Ilimitado",
          "enterprise": "Ilimitado"
        },
        {
          "name": "Permissões granulares",
          "starter": false,
          "professional": true,
          "enterprise": true
        },
        {
          "name": "Workspaces múltiplos",
          "starter": false,
          "professional": false,
          "enterprise": true
        }
      ]
    },
      {
        "name": "Suporte",
      "features": [
        {
          "name": "Suporte por email",
          "starter": true,
          "professional": true,
          "enterprise": true
        },
        {
          "name": "Suporte prioritário",
          "starter": false,
          "professional": true,
          "enterprise": true
        },
        {
          "name": "Suporte 24/7",
          "starter": false,
          "professional": false,
          "enterprise": true
        },
        {
          "name": "Gerente de conta dedicado",
          "starter": false,
          "professional": false,
          "enterprise": true
        }
      ]
      }
    ]
  },
  "credit_packs": [
    {
      "id": "pack-reports-small",
      "name": "Pacote Pequeno - Relatórios",
      "description": "Para necessidades pontuais de relatórios",
      "credits": 20,
      "price": 97,
      "type": "reports",
      "popular": false
    },
    {
      "id": "pack-reports-medium",
      "name": "Pacote Médio - Relatórios",
      "description": "Melhor custo-benefício em relatórios",
      "credits": 50,
      "price": 197,
      "type": "reports",
      "savings": "15%",
      "popular": true
    },
    {
      "id": "pack-reports-large",
      "name": "Pacote Grande - Relatórios",
      "description": "Máxima economia em relatórios",
      "credits": 120,
      "price": 397,
      "type": "reports",
      "savings": "25%",
      "popular": false
    },
    {
      "id": "pack-analysis-small",
      "name": "Pacote Pequeno - Análises",
      "description": "Para análises IA pontuais",
      "credits": 5,
      "price": 97,
      "type": "analysis",
      "popular": false
    },
    {
      "id": "pack-analysis-medium",
      "name": "Pacote Médio - Análises",
      "description": "Melhor custo-benefício em análises",
      "credits": 15,
      "price": 197,
      "type": "analysis",
      "savings": "15%",
      "popular": false
    },
    {
      "id": "pack-analysis-large",
      "name": "Pacote Grande - Análises",
      "description": "Máxima economia em análises",
      "credits": 40,
      "price": 397,
      "type": "analysis",
      "savings": "25%",
      "popular": false
    }
  ],
  "faq": [
    {
      "question": "O que são créditos de análise completa?",
      "answer": "Créditos de análises completas são usados para análises profundas de processos que exigem processamento extra via nossa IA. Cada análise completa consome 1 crédito e inclui extração avançada de dados, análise de riscos, e insights detalhados."
    },
    {
      "question": "Os relatórios são realmente ilimitados?",
      "answer": "Para proteção da plataforma e garantia de qualidade, aplicamos limites de fair-use por plano. No plano Starter são 20 relatórios/mês, no Professional 60 relatórios/mês. O plano Enterprise tem limites personalizados conforme acordo."
    },
    {
      "question": "Como funciona o desconto anual?",
      "answer": "Assinando anualmente, você economiza 15% em relação ao pagamento mensal. O valor é cobrado uma única vez no ano, e você pode cancelar a qualquer momento com reembolso proporcional."
    },
    {
      "question": "Posso cancelar a qualquer momento?",
      "answer": "Sim! Você pode cancelar sua assinatura a qualquer momento sem multas ou taxas adicionais. Se cancelar um plano anual, fazemos o reembolso proporcional dos meses não utilizados."
    },
    {
      "question": "O que acontece com meus créditos não utilizados?",
      "answer": "Créditos de relatório podem acumular até 36 créditos (Starter) ou 120 créditos (Professional). Créditos de análise completa podem acumular até 50 (Starter) ou mais conforme o plano. Créditos expiram seguindo a regra FIFO."
    },
    {
      "question": "Posso adicionar mais usuários?",
      "answer": "No plano Starter, você tem 3 usuários incluídos. Nos planos Professional e Enterprise, usuários são ilimitados. Você pode gerenciar permissões e acessos pelo painel administrativo."
    },
    {
      "question": "Como funciona o teste gratuito?",
      "answer": "Oferecemos 7 dias de teste gratuito nos planos Starter e Professional, e 14 dias no Enterprise. Não é necessário cartão de crédito para começar. Você tem acesso completo a todas as funcionalidades do plano durante o período de teste."
    },
    {
      "question": "Posso mudar de plano depois?",
      "answer": "Sim! Você pode fazer upgrade ou downgrade do seu plano a qualquer momento. Em caso de upgrade, o valor é ajustado proporcionalmente. Em caso de downgrade, o ajuste é aplicado no próximo ciclo de cobrança."
    }
  ]
}
